cc_plugin_wcrp-1.1.0.dist-info/licenses/LICENSE
checks/utils.py
checks/attribute_checks/check_attribute_cv.py
checks/attribute_checks/check_attribute_suite.py
checks/attribute_checks/check_attrs_cordex_cmip6.py
checks/consistency_checks/check_attributes_match_filename.py
checks/consistency_checks/check_drs_consistency.py
checks/consistency_checks/check_drs_filename_cv.py
checks/consistency_checks/check_experiment_consistency.py
checks/consistency_checks/check_frequency_table_consistency.py
checks/consistency_checks/check_institution_source_consistency.py
checks/consistency_checks/check_variant_label_consistency.py
checks/data_plausibility_checks/__init__.py
checks/data_plausibility_checks/check_chunk_size.py
checks/data_plausibility_checks/check_constant.py
checks/data_plausibility_checks/check_fill_missing.py
checks/data_plausibility_checks/check_nan_inf.py
checks/data_plausibility_checks/check_spatial_statistical_outliers.py
checks/data_plausibility_checks/detect_physically_impossible_outlier.py
checks/data_plausibility_checks/outliers_thresholds.json
checks/data_plausibility_checks/utils/auxiliar.py
checks/data_plausibility_checks/utils/data.py
checks/data_plausibility_checks/utils/dimensions.py
checks/dimension_checks/check_dimension_existence.py
checks/dimension_checks/check_dimension_positive.py
checks/dimension_checks/check_dimension_size.py
checks/format_checks/check_compression.py
checks/format_checks/check_format.py
checks/time_checks/check_time_bounds.py
checks/time_checks/check_time_calendar.py
checks/time_checks/check_time_cordex_cmip6.py
checks/time_checks/check_time_range_vs_filename.py
checks/time_checks/check_time_squareness.py
checks/time_checks/time_constants.py
checks/variable_checks/check_bounds_value_consistency.py
checks/variable_checks/check_coords_cordex_cmip6.py
checks/variable_checks/check_data_types.py
checks/variable_checks/check_variable_existence.py
checks/variable_checks/check_variable_shape_vs_dimensions.py
checks/variable_checks/check_variable_type.py
plugins/__init__.py
cc_plugin_wcrp-1.1.0.dist-info/METADATA
cc_plugin_wcrp-1.1.0.dist-info/WHEEL
cc_plugin_wcrp-1.1.0.dist-info/entry_points.txt
cc_plugin_wcrp-1.1.0.dist-info/top_level.txt
cc_plugin_wcrp-1.1.0.dist-info/RECORD
