Metadata-Version: 2.4
Name: cc-plugin-wcrp
Version: 1.1.0
Summary: This IOOS Compliance-Checker plugins checks compliance with WCRP Projects specifications 
Author-email: Ayoub Nachite <anachite@ipsl.fr>, Martin Schupfner <schupfner@dkrz.de>, Javier Diez-Sierra <javier.diez@unican.es>, Rubén García Macho <rubengm@ifca.unican.es>, Adrian Chantreux <chantreux@ifca.unican.es>
Maintainer-email: Ayoub Nachite <anachite@ipsl.fr>
License:                                  Apache License
Keywords: compliance checker,plugin,esgf-qc,esgf-qa,wcrp,cmip6,cordex_cmip6
Requires-Python: >=3.10
License-File: LICENSE
Requires-Dist: compliance-checker>=5.1.2
Requires-Dist: netCDF4
Requires-Dist: xarray
Requires-Dist: pandas
Requires-Dist: cftime
Requires-Dist: toml
Requires-Dist: cf_xarray
Requires-Dist: esgvoc
Requires-Dist: pooch
Requires-Dist: pydantic>=2.12.5
Dynamic: license-file
